{
  "validate_on_submit": true,
  "show_errors_on_submit": false,
  "count": "1",
  "encounter_type": "PPFP",
  "entity_id": "",
  "relational_id": "",
  "metadata": {
    "start": {
      "openmrs_entity_parent": "",
      "openmrs_entity": "concept",
      "openmrs_data_type": "start",
      "openmrs_entity_id": "163137AAAAAAAAAAAAAAAAAAAAAAAAAAAAAA"
    },
    "end": {
      "openmrs_entity_parent": "",
      "openmrs_entity": "concept",
      "openmrs_data_type": "end",
      "openmrs_entity_id": "163138AAAAAAAAAAAAAAAAAAAAAAAAAAAAAA"
    },
    "deviceid": {
      "openmrs_entity_parent": "",
      "openmrs_entity": "concept",
      "openmrs_data_type": "deviceid",
      "openmrs_entity_id": "163149AAAAAAAAAAAAAAAAAAAAAAAAAAAAAA"
    },
    "subscriberid": {
      "openmrs_entity_parent": "",
      "openmrs_entity": "concept",
      "openmrs_data_type": "subscriberid",
      "openmrs_entity_id": "163150AAAAAAAAAAAAAAAAAAAAAAAAAAAAAA"
    },
    "simserial": {
      "openmrs_entity_parent": "",
      "openmrs_entity": "concept",
      "openmrs_data_type": "simserial",
      "openmrs_entity_id": "163151AAAAAAAAAAAAAAAAAAAAAAAAAAAAAA"
    },
    "phonenumber": {
      "openmrs_entity_parent": "",
      "openmrs_entity": "concept",
      "openmrs_data_type": "phonenumber",
      "openmrs_entity_id": "163152AAAAAAAAAAAAAAAAAAAAAAAAAAAAAA"
    },
    "encounter_location": "",
    "look_up": {
      "entity_id": "",
      "value": ""
    }
  },
  "step1": {
    "title": "Post-Partum Family Planning (PPFP)",
    "fields": [
      {
        "key": "ppfp",
        "openmrs_entity_parent": "",
        "openmrs_entity": "concept",
        "openmrs_entity_id": "ppfp",
        "label": "Post-Partum Family Planning (PPFP)",
        "text_color": "#000000",
        "type": "native_radio",
        "options": [
          {
            "key": "yes",
            "text": "Yes",
            "openmrs_entity_parent": "",
            "openmrs_entity": "concept",
            "openmrs_entity_id": "yes"
          },
          {
            "key": "no",
            "text": "No",
            "openmrs_entity_parent": "",
            "openmrs_entity": "concept",
            "openmrs_entity_id": "no"
          }
        ],
        "v_required": {
          "value": true,
          "err": "Please select an option"
        }
      },
      {
        "key": "ppfp_method",
        "openmrs_entity_parent": "",
        "openmrs_entity": "concept",
        "openmrs_entity_id": "ppfp_method",
        "label": "Post-Partum Family Planning (PPFP) Method",
        "text_color": "#000000",
        "type": "native_radio",
        "options": [
          {
            "key": "iucd",
            "text": "IUCD",
            "openmrs_entity_parent": "",
            "openmrs_entity": "concept",
            "openmrs_entity_id": "iucd"
          },
          {
            "key": "implants",
            "text": "Implants",
            "openmrs_entity_parent": "",
            "openmrs_entity": "concept",
            "openmrs_entity_id": "implants"
          },
          {
            "key": "btl",
            "text": "BTL",
            "openmrs_entity_parent": "",
            "openmrs_entity": "concept",
            "openmrs_entity_id": "btl"
          },
          {
            "key": "pop",
            "text": "Progesterone only pills (POP)",
            "openmrs_entity_parent": "",
            "openmrs_entity": "concept",
            "openmrs_entity_id": "pop"
          },
          {
            "key": "condom",
            "text": "Condom",
            "openmrs_entity_parent": "",
            "openmrs_entity": "concept",
            "openmrs_entity_id": "condom"
          }
        ],
        "v_required": {
          "value": true,
          "err": "Please select an option"
        },
        "relevance": {
          "step1:ppfp": {
            "type": "string",
            "ex": "equalTo(., \"yes\")"
          }
        }
      }
    ]
  }
}